[
    {
        "ID": 1,
        "time_begin": 1400,
        "track": 2,
        "type": 3,
        "time_end": 1650
    },
    {
        "ID": 2,
        "time_begin": 1400,
        "track": 2,
        "type": 3,
        "time_end": 1650
    },
    {
        "ID": 3,
        "time_begin": 1400,
        "track": 2,
        "type": 6,
        "time_end": 2148
    },
    {
        "ID": 4,
        "time_begin": 1400,
        "track": 2,
        "type": 3,
        "time_end": 1650
    },
    {
        "ID": 5,
        "time_begin": 1400,
        "track": 2,
        "type": 3,
        "time_end": 1650
    },
    {
        "ID": 6,
        "time_begin": 2000,
        "track": 2,
        "type": 3,
        "time_end": 2250
    },
    {
        "ID": 7,
        "time_begin": 2000,
        "track": 2,
        "type": 3,
        "time_end": 2250
    },
    {
        "ID": 8,
        "time_begin": 2000,
        "track": 2,
        "type": 3,
        "time_end": 2250
    },
    {
        "ID": 9,
        "time_begin": 2000,
        "track": 2,
        "type": 3,
        "time_end": 2250
    },
    {
        "ID": 10,
        "time_begin": 2148,
        "track": 2,
        "type": 6,
        "time_end": 2911
    },
    {
        "ID": 11,
        "time_begin": 2200,
        "track": 1,
        "type": 10,
        "time_end": 0
    },
    {
        "ID": 12,
        "time_begin": 2200,
        "track": 2,
        "type": 10,
        "time_end": 0
    },
    {
        "ID": 13,
        "time_begin": 2600,
        "track": 1,
        "type": 10,
        "time_end": 0
    },
    {
        "ID": 14,
        "time_begin": 2600,
        "track": 2,
        "type": 10,
        "time_end": 0
    },
    {
        "ID": 15,
        "time_begin": 2911,
        "track": 2,
        "type": 6,
        "time_end": 3200
    },
    {
        "ID": 16,
        "time_begin": 3000,
        "track": 1,
        "type": 10,
        "time_end": 0
    },
    {
        "ID": 17,
        "time_begin": 3000,
        "track": 2,
        "type": 10,
        "time_end": 0
    },
    {
        "ID": 18,
        "time_begin": 3200,
        "track": 2,
        "type": 3,
        "time_end": 3450
    },
    {
        "ID": 19,
        "time_begin": 3200,
        "track": 2,
        "type": 3,
        "time_end": 3450
    },
    {
        "ID": 20,
        "time_begin": 3200,
        "track": 2,
        "type": 0,
        "time_end": 0
    },
    {
        "ID": 21,
        "time_begin": 3200,
        "track": 2,
        "type": 3,
        "time_end": 3450
    },
    {
        "ID": 22,
        "time_begin": 3200,
        "track": 2,
        "type": 3,
        "time_end": 3450
    },
    {
        "ID": 23,
        "time_begin": 4182,
        "track": 1,
        "type": 0,
        "time_end": 0
    },
    {
        "ID": 24,
        "time_begin": 4945,
        "track": 2,
        "type": 3,
        "time_end": 5195
    },
    {
        "ID": 25,
        "time_begin": 5400,
        "track": 2,
        "type": 3,
        "time_end": 5650
    },
    {
        "ID": 26,
        "time_begin": 5400,
        "track": 2,
        "type": 3,
        "time_end": 5650
    },
    {
        "ID": 27,
        "time_begin": 5400,
        "track": 2,
        "type": 3,
        "time_end": 5650
    },
    {
        "ID": 28,
        "time_begin": 5400,
        "track": 2,
        "type": 6,
        "time_end": 6216
    },
    {
        "ID": 29,
        "time_begin": 5400,
        "track": 2,
        "type": 3,
        "time_end": 5650
    },
    {
        "ID": 30,
        "time_begin": 6000,
        "track": 2,
        "type": 3,
        "time_end": 6250
    },
    {
        "ID": 31,
        "time_begin": 6000,
        "track": 2,
        "type": 3,
        "time_end": 6250
    },
    {
        "ID": 32,
        "time_begin": 6000,
        "track": 2,
        "type": 3,
        "time_end": 6250
    },
    {
        "ID": 33,
        "time_begin": 6000,
        "track": 2,
        "type": 3,
        "time_end": 6250
    },
    {
        "ID": 34,
        "time_begin": 6200,
        "track": 1,
        "type": 10,
        "time_end": 0
    },
    {
        "ID": 35,
        "time_begin": 6216,
        "track": 2,
        "type": 6,
        "time_end": 6979
    },
    {
        "ID": 36,
        "time_begin": 6600,
        "track": 1,
        "type": 10,
        "time_end": 0
    },
    {
        "ID": 37,
        "time_begin": 6979,
        "track": 2,
        "type": 6,
        "time_end": 7200
    },
    {
        "ID": 38,
        "time_begin": 7000,
        "track": 1,
        "type": 10,
        "time_end": 0
    },
    {
        "ID": 39,
        "time_begin": 7200,
        "track": 2,
        "type": 3,
        "time_end": 7450
    },
    {
        "ID": 40,
        "time_begin": 7200,
        "track": 2,
        "type": 3,
        "time_end": 7450
    },
    {
        "ID": 41,
        "time_begin": 7200,
        "track": 2,
        "type": 3,
        "time_end": 7450
    },
    {
        "ID": 42,
        "time_begin": 7200,
        "track": 2,
        "type": 0,
        "time_end": 0
    },
    {
        "ID": 43,
        "time_begin": 7200,
        "track": 2,
        "type": 3,
        "time_end": 7450
    },
    {
        "ID": 44,
        "time_begin": 8250,
        "track": 2,
        "type": 0,
        "time_end": 0
    },
    {
        "ID": 45,
        "time_begin": 9013,
        "track": 2,
        "type": 3,
        "time_end": 9263
    },
    {
        "ID": 46,
        "time_begin": 9400,
        "track": 1,
        "type": 6,
        "time_end": 10284
    },
    {
        "ID": 47,
        "time_begin": 9400,
        "track": 2,
        "type": 3,
        "time_end": 9650
    },
    {
        "ID": 48,
        "time_begin": 9400,
        "track": 2,
        "type": 3,
        "time_end": 9650
    },
    {
        "ID": 49,
        "time_begin": 9400,
        "track": 2,
        "type": 3,
        "time_end": 9650
    },
    {
        "ID": 50,
        "time_begin": 9400,
        "track": 2,
        "type": 3,
        "time_end": 9650
    },
    {
        "ID": 51,
        "time_begin": 10000,
        "track": 2,
        "type": 3,
        "time_end": 10250
    },
    {
        "ID": 52,
        "time_begin": 10000,
        "track": 2,
        "type": 3,
        "time_end": 10250
    },
    {
        "ID": 53,
        "time_begin": 10000,
        "track": 2,
        "type": 3,
        "time_end": 10250
    },
    {
        "ID": 54,
        "time_begin": 10000,
        "track": 2,
        "type": 3,
        "time_end": 10250
    },
    {
        "ID": 55,
        "time_begin": 10200,
        "track": 2,
        "type": 10,
        "time_end": 0
    },
    {
        "ID": 56,
        "time_begin": 10284,
        "track": 1,
        "type": 6,
        "time_end": 11047
    },
    {
        "ID": 57,
        "time_begin": 10600,
        "track": 2,
        "type": 10,
        "time_end": 0
    },
    {
        "ID": 58,
        "time_begin": 11000,
        "track": 2,
        "type": 10,
        "time_end": 0
    },
    {
        "ID": 59,
        "time_begin": 11047,
        "track": 1,
        "type": 6,
        "time_end": 11200
    },
    {
        "ID": 60,
        "time_begin": 11200,
        "track": 1,
        "type": 0,
        "time_end": 0
    },
    {
        "ID": 61,
        "time_begin": 11200,
        "track": 2,
        "type": 3,
        "time_end": 11450
    },
    {
        "ID": 62,
        "time_begin": 11200,
        "track": 2,
        "type": 3,
        "time_end": 11450
    },
    {
        "ID": 63,
        "time_begin": 11200,
        "track": 2,
        "type": 3,
        "time_end": 11450
    },
    {
        "ID": 64,
        "time_begin": 11200,
        "track": 2,
        "type": 3,
        "time_end": 11450
    },
    {
        "ID": 65,
        "time_begin": 12318,
        "track": 2,
        "type": 0,
        "time_end": 0
    },
    {
        "ID": 66,
        "time_begin": 14352,
        "track": 2,
        "type": 0,
        "time_end": 0
    },
    {
        "ID": 67,
        "time_begin": 15877,
        "track": 2,
        "type": 6,
        "time_end": 16386
    },
    {
        "ID": 68,
        "time_begin": 16386,
        "track": 2,
        "type": 6,
        "time_end": 16725
    },
    {
        "ID": 69,
        "time_begin": 16725,
        "track": 2,
        "type": 6,
        "time_end": 17148
    },
    {
        "ID": 70,
        "time_begin": 17148,
        "track": 2,
        "type": 6,
        "time_end": 17911
    },
    {
        "ID": 71,
        "time_begin": 17911,
        "track": 1,
        "type": 6,
        "time_end": 17911
    },
    {
        "ID": 72,
        "time_begin": 17911,
        "track": 2,
        "type": 6,
        "time_end": 18928
    },
    {
        "ID": 73,
        "time_begin": 18928,
        "track": 1,
        "type": 6,
        "time_end": 18928
    },
    {
        "ID": 74,
        "time_begin": 18928,
        "track": 2,
        "type": 6,
        "time_end": 19945
    },
    {
        "ID": 75,
        "time_begin": 19945,
        "track": 1,
        "type": 6,
        "time_end": 20453
    },
    {
        "ID": 76,
        "time_begin": 20453,
        "track": 1,
        "type": 6,
        "time_end": 20792
    },
    {
        "ID": 77,
        "time_begin": 20792,
        "track": 1,
        "type": 6,
        "time_end": 21216
    },
    {
        "ID": 78,
        "time_begin": 21216,
        "track": 1,
        "type": 6,
        "time_end": 21979
    },
    {
        "ID": 79,
        "time_begin": 21979,
        "track": 1,
        "type": 6,
        "time_end": 21979
    },
    {
        "ID": 80,
        "time_begin": 21979,
        "track": 2,
        "type": 6,
        "time_end": 21979
    },
    {
        "ID": 81,
        "time_begin": 21979,
        "track": 3,
        "type": 6,
        "time_end": 22996
    },
    {
        "ID": 82,
        "time_begin": 22996,
        "track": 1,
        "type": 6,
        "time_end": 22996
    },
    {
        "ID": 83,
        "time_begin": 22996,
        "track": 2,
        "type": 6,
        "time_end": 22996
    },
    {
        "ID": 84,
        "time_begin": 22996,
        "track": 3,
        "type": 6,
        "time_end": 24013
    },
    {
        "ID": 85,
        "time_begin": 24013,
        "track": 2,
        "type": 6,
        "time_end": 24521
    },
    {
        "ID": 86,
        "time_begin": 24521,
        "track": 2,
        "type": 6,
        "time_end": 24860
    },
    {
        "ID": 87,
        "time_begin": 24860,
        "track": 2,
        "type": 6,
        "time_end": 25284
    },
    {
        "ID": 88,
        "time_begin": 25284,
        "track": 2,
        "type": 6,
        "time_end": 26047
    },
    {
        "ID": 89,
        "time_begin": 26047,
        "track": 3,
        "type": 6,
        "time_end": 26047
    },
    {
        "ID": 90,
        "time_begin": 26047,
        "track": 2,
        "type": 6,
        "time_end": 26047
    },
    {
        "ID": 91,
        "time_begin": 26047,
        "track": 1,
        "type": 6,
        "time_end": 27064
    },
    {
        "ID": 92,
        "time_begin": 27064,
        "track": 3,
        "type": 6,
        "time_end": 27064
    },
    {
        "ID": 93,
        "time_begin": 27064,
        "track": 2,
        "type": 6,
        "time_end": 27064
    },
    {
        "ID": 94,
        "time_begin": 27064,
        "track": 1,
        "type": 6,
        "time_end": 28081
    },
    {
        "ID": 95,
        "time_begin": 28081,
        "track": 2,
        "type": 6,
        "time_end": 28589
    },
    {
        "ID": 96,
        "time_begin": 28589,
        "track": 2,
        "type": 6,
        "time_end": 28928
    },
    {
        "ID": 97,
        "time_begin": 28928,
        "track": 2,
        "type": 6,
        "time_end": 29267
    },
    {
        "ID": 98,
        "time_begin": 29267,
        "track": 2,
        "type": 6,
        "time_end": 30114
    },
    {
        "ID": 99,
        "time_begin": 30114,
        "track": 1,
        "type": 6,
        "time_end": 30114
    },
    {
        "ID": 100,
        "time_begin": 30114,
        "track": 2,
        "type": 6,
        "time_end": 31131
    },
    {
        "ID": 101,
        "time_begin": 31131,
        "track": 1,
        "type": 6,
        "time_end": 31131
    },
    {
        "ID": 102,
        "time_begin": 31131,
        "track": 2,
        "type": 6,
        "time_end": 32148
    },
    {
        "ID": 103,
        "time_begin": 32148,
        "track": 2,
        "type": 0,
        "time_end": 0
    },
    {
        "ID": 104,
        "time_begin": 35453,
        "track": 1,
        "type": 0,
        "time_end": 0
    },
    {
        "ID": 105,
        "time_begin": 35453,
        "track": 1,
        "type": 0,
        "time_end": 0
    },
    {
        "ID": 106,
        "time_begin": 35453,
        "track": 2,
        "type": 0,
        "time_end": 0
    },
    {
        "ID": 107,
        "time_begin": 35453,
        "track": 2,
        "type": 0,
        "time_end": 0
    },
    {
        "ID": 108,
        "time_begin": 35453,
        "track": 3,
        "type": 0,
        "time_end": 0
    }
]
