[
    {
        "ID": 1,
        "time_begin": 1571,
        "track": 2,
        "type": 0,
        "time_end": 0
    },
    {
        "ID": 2,
        "time_begin": 3000,
        "track": 1,
        "type": 6,
        "time_end": 3206
    },
    {
        "ID": 3,
        "time_begin": 3000,
        "track": 1,
        "type": 6,
        "time_end": 3206
    },
    {
        "ID": 4,
        "time_begin": 3000,
        "track": 2,
        "type": 3,
        "time_end": 3250
    },
    {
        "ID": 5,
        "time_begin": 3000,
        "track": 2,
        "type": 6,
        "time_end": 3206
    },
    {
        "ID": 6,
        "time_begin": 3000,
        "track": 3,
        "type": 6,
        "time_end": 3206
    },
    {
        "ID": 7,
        "time_begin": 3206,
        "track": 2,
        "type": 6,
        "time_end": 3206
    },
    {
        "ID": 8,
        "time_begin": 3206,
        "track": 1,
        "type": 6,
        "time_end": 3533
    },
    {
        "ID": 9,
        "time_begin": 3533,
        "track": 2,
        "type": 6,
        "time_end": 3533
    },
    {
        "ID": 10,
        "time_begin": 3533,
        "track": 1,
        "type": 6,
        "time_end": 3600
    },
    {
        "ID": 11,
        "time_begin": 3600,
        "track": 1,
        "type": 0,
        "time_end": 0
    },
    {
        "ID": 12,
        "time_begin": 3600,
        "track": 1,
        "type": 0,
        "time_end": 0
    },
    {
        "ID": 13,
        "time_begin": 3600,
        "track": 2,
        "type": 3,
        "time_end": 3850
    },
    {
        "ID": 14,
        "time_begin": 3600,
        "track": 2,
        "type": 0,
        "time_end": 0
    },
    {
        "ID": 15,
        "time_begin": 3600,
        "track": 3,
        "type": 0,
        "time_end": 0
    },
    {
        "ID": 16,
        "time_begin": 3861,
        "track": 3,
        "type": 0,
        "time_end": 0
    },
    {
        "ID": 17,
        "time_begin": 3861,
        "track": 1,
        "type": 0,
        "time_end": 0
    },
    {
        "ID": 18,
        "time_begin": 4188,
        "track": 3,
        "type": 0,
        "time_end": 0
    },
    {
        "ID": 19,
        "time_begin": 4188,
        "track": 1,
        "type": 0,
        "time_end": 0
    },
    {
        "ID": 20,
        "time_begin": 6800,
        "track": 2,
        "type": 3,
        "time_end": 7050
    },
    {
        "ID": 21,
        "time_begin": 6800,
        "track": 2,
        "type": 3,
        "time_end": 7050
    },
    {
        "ID": 22,
        "time_begin": 6800,
        "track": 2,
        "type": 3,
        "time_end": 7050
    },
    {
        "ID": 23,
        "time_begin": 6805,
        "track": 2,
        "type": 0,
        "time_end": 0
    },
    {
        "ID": 24,
        "time_begin": 7000,
        "track": 2,
        "type": 3,
        "time_end": 7250
    },
    {
        "ID": 25,
        "time_begin": 7000,
        "track": 2,
        "type": 3,
        "time_end": 7250
    },
    {
        "ID": 26,
        "time_begin": 7000,
        "track": 2,
        "type": 3,
        "time_end": 7250
    },
    {
        "ID": 27,
        "time_begin": 7200,
        "track": 2,
        "type": 3,
        "time_end": 7450
    },
    {
        "ID": 28,
        "time_begin": 7200,
        "track": 2,
        "type": 3,
        "time_end": 7450
    },
    {
        "ID": 29,
        "time_begin": 7200,
        "track": 2,
        "type": 3,
        "time_end": 7450
    },
    {
        "ID": 30,
        "time_begin": 7400,
        "track": 2,
        "type": 3,
        "time_end": 7650
    },
    {
        "ID": 31,
        "time_begin": 7400,
        "track": 2,
        "type": 3,
        "time_end": 7650
    },
    {
        "ID": 32,
        "time_begin": 7400,
        "track": 2,
        "type": 3,
        "time_end": 7650
    },
    {
        "ID": 33,
        "time_begin": 7459,
        "track": 2,
        "type": 0,
        "time_end": 0
    },
    {
        "ID": 34,
        "time_begin": 7600,
        "track": 2,
        "type": 3,
        "time_end": 7850
    },
    {
        "ID": 35,
        "time_begin": 7600,
        "track": 2,
        "type": 3,
        "time_end": 7850
    },
    {
        "ID": 36,
        "time_begin": 7600,
        "track": 2,
        "type": 3,
        "time_end": 7850
    },
    {
        "ID": 37,
        "time_begin": 7800,
        "track": 2,
        "type": 3,
        "time_end": 8050
    },
    {
        "ID": 38,
        "time_begin": 7800,
        "track": 2,
        "type": 3,
        "time_end": 8050
    },
    {
        "ID": 39,
        "time_begin": 7800,
        "track": 2,
        "type": 3,
        "time_end": 8050
    },
    {
        "ID": 40,
        "time_begin": 8000,
        "track": 2,
        "type": 3,
        "time_end": 8250
    },
    {
        "ID": 41,
        "time_begin": 8000,
        "track": 2,
        "type": 3,
        "time_end": 8250
    },
    {
        "ID": 42,
        "time_begin": 8000,
        "track": 2,
        "type": 3,
        "time_end": 8250
    },
    {
        "ID": 43,
        "time_begin": 8114,
        "track": 2,
        "type": 0,
        "time_end": 0
    },
    {
        "ID": 44,
        "time_begin": 8200,
        "track": 2,
        "type": 3,
        "time_end": 8450
    },
    {
        "ID": 45,
        "time_begin": 8200,
        "track": 2,
        "type": 3,
        "time_end": 8450
    },
    {
        "ID": 46,
        "time_begin": 8200,
        "track": 2,
        "type": 3,
        "time_end": 8450
    },
    {
        "ID": 47,
        "time_begin": 10731,
        "track": 2,
        "type": 6,
        "time_end": 11385
    },
    {
        "ID": 48,
        "time_begin": 11385,
        "track": 2,
        "type": 6,
        "time_end": 11712
    },
    {
        "ID": 49,
        "time_begin": 11712,
        "track": 2,
        "type": 6,
        "time_end": 12039
    },
    {
        "ID": 50,
        "time_begin": 12039,
        "track": 2,
        "type": 6,
        "time_end": 12694
    },
    {
        "ID": 51,
        "time_begin": 12694,
        "track": 1,
        "type": 6,
        "time_end": 13348
    },
    {
        "ID": 52,
        "time_begin": 13348,
        "track": 1,
        "type": 6,
        "time_end": 13675
    },
    {
        "ID": 53,
        "time_begin": 13675,
        "track": 1,
        "type": 6,
        "time_end": 14002
    },
    {
        "ID": 54,
        "time_begin": 13675,
        "track": 2,
        "type": 14,
        "time_end": 0
    },
    {
        "ID": 55,
        "time_begin": 14002,
        "track": 1,
        "type": 6,
        "time_end": 14657
    },
    {
        "ID": 56,
        "time_begin": 14657,
        "track": 1,
        "type": 6,
        "time_end": 15311
    },
    {
        "ID": 57,
        "time_begin": 15311,
        "track": 2,
        "type": 6,
        "time_end": 15965
    },
    {
        "ID": 58,
        "time_begin": 15965,
        "track": 1,
        "type": 6,
        "time_end": 16620
    },
    {
        "ID": 59,
        "time_begin": 16620,
        "track": 2,
        "type": 6,
        "time_end": 16947
    },
    {
        "ID": 60,
        "time_begin": 16947,
        "track": 2,
        "type": 6,
        "time_end": 17274
    },
    {
        "ID": 61,
        "time_begin": 17274,
        "track": 2,
        "type": 6,
        "time_end": 17928
    },
    {
        "ID": 62,
        "time_begin": 17928,
        "track": 2,
        "type": 6,
        "time_end": 18582
    },
    {
        "ID": 63,
        "time_begin": 18582,
        "track": 3,
        "type": 6,
        "time_end": 18910
    },
    {
        "ID": 64,
        "time_begin": 18910,
        "track": 3,
        "type": 6,
        "time_end": 19237
    },
    {
        "ID": 65,
        "time_begin": 19237,
        "track": 3,
        "type": 6,
        "time_end": 19891
    },
    {
        "ID": 66,
        "time_begin": 19891,
        "track": 2,
        "type": 6,
        "time_end": 20545
    },
    {
        "ID": 67,
        "time_begin": 20545,
        "track": 1,
        "type": 6,
        "time_end": 21200
    },
    {
        "ID": 68,
        "time_begin": 21200,
        "track": 2,
        "type": 6,
        "time_end": 21854
    },
    {
        "ID": 69,
        "time_begin": 21854,
        "track": 2,
        "type": 6,
        "time_end": 22181
    },
    {
        "ID": 70,
        "time_begin": 22181,
        "track": 2,
        "type": 6,
        "time_end": 22508
    },
    {
        "ID": 71,
        "time_begin": 22508,
        "track": 2,
        "type": 6,
        "time_end": 23163
    },
    {
        "ID": 72,
        "time_begin": 23163,
        "track": 2,
        "type": 6,
        "time_end": 23817
    },
    {
        "ID": 73,
        "time_begin": 23817,
        "track": 1,
        "type": 6,
        "time_end": 24471
    },
    {
        "ID": 74,
        "time_begin": 24471,
        "track": 1,
        "type": 6,
        "time_end": 25126
    },
    {
        "ID": 75,
        "time_begin": 25126,
        "track": 1,
        "type": 6,
        "time_end": 26107
    },
    {
        "ID": 76,
        "time_begin": 26107,
        "track": 3,
        "type": 6,
        "time_end": 26107
    },
    {
        "ID": 77,
        "time_begin": 26107,
        "track": 2,
        "type": 6,
        "time_end": 26107
    },
    {
        "ID": 78,
        "time_begin": 26107,
        "track": 1,
        "type": 6,
        "time_end": 26107
    },
    {
        "ID": 79,
        "time_begin": 26107,
        "track": 1,
        "type": 6,
        "time_end": 26107
    },
    {
        "ID": 80,
        "time_begin": 26107,
        "track": 2,
        "type": 6,
        "time_end": 27088
    },
    {
        "ID": 81,
        "time_begin": 27088,
        "track": 2,
        "type": 0,
        "time_end": 0
    },
    {
        "ID": 82,
        "time_begin": 30687,
        "track": 1,
        "type": 0,
        "time_end": 0
    },
    {
        "ID": 83,
        "time_begin": 30687,
        "track": 2,
        "type": 0,
        "time_end": 0
    }
]
