[
    {
        "ID": 1,
        "track": 1,
        "type": 0,
        "time_begin": 18,
        "time_end": 0,
        "background": 0
    },
    {
        "ID": 2,
        "track": 2,
        "type": 0,
        "time_begin": 370,
        "time_end": 0,
        "background": 0
    },
    {
        "ID": 3,
        "track": 3,
        "type": 1,
        "time_begin": 780,
        "time_end": 1542,
        "background": 0
    },
    {
        "ID": 4,
        "track": 1,
        "type": 0,
        "time_begin": 1893,
        "time_end": 0,
        "background": 0
    },
    {
        "ID": 5,
        "track": 3,
        "type": 0,
        "time_begin": 2245,
        "time_end": 0,
        "background": 0
    },
    {
        "ID": 6,
        "track": 2,
        "type": 1,
        "time_begin": 2655,
        "time_end": 3417,
        "background": 0
    },
    {
        "ID": 7,
        "track": 4,
        "type": 1,
        "time_begin": 3768,
        "time_end": 4706,
        "background": 0
    },
    {
        "ID": 8,
        "track": 3,
        "type": 1,
        "time_begin": 4706,
        "time_end": 5643,
        "background": 0
    },
    {
        "ID": 9,
        "track": 1,
        "type": 0,
        "time_begin": 5643,
        "time_end": 0,
        "background": 0
    },
    {
        "ID": 10,
        "track": 3,
        "type": 0,
        "time_begin": 6112,
        "time_end": 0,
        "background": 0
    },
    {
        "ID": 11,
        "track": 2,
        "type": 0,
        "time_begin": 6581,
        "time_end": 0,
        "background": 0
    },
    {
        "ID": 12,
        "track": 4,
        "type": 0,
        "time_begin": 7050,
        "time_end": 0,
        "background": 0
    },
    {
        "ID": 13,
        "track": 1,
        "type": 0,
        "time_begin": 7518,
        "time_end": 0,
        "background": 1
    },
    {
        "ID": 14,
        "track": 3,
        "type": 0,
        "time_begin": 7518,
        "time_end": 0,
        "background": 1
    },
    {
        "ID": 15,
        "track": 2,
        "type": 0,
        "time_begin": 7987,
        "time_end": 0,
        "background": 0
    },
    {
        "ID": 16,
        "track": 3,
        "type": 0,
        "time_begin": 8221,
        "time_end": 0,
        "background": 0
    },
    {
        "ID": 17,
        "track": 2,
        "type": 1,
        "time_begin": 8456,
        "time_end": 8925,
        "background": 0
    },
    {
        "ID": 18,
        "track": 4,
        "type": 1,
        "time_begin": 8925,
        "time_end": 9393,
        "background": 0
    },
    {
        "ID": 19,
        "track": 3,
        "type": 0,
        "time_begin": 9393,
        "time_end": 0,
        "background": 0
    },
    {
        "ID": 20,
        "track": 2,
        "type": 0,
        "time_begin": 9628,
        "time_end": 0,
        "background": 0
    },
    {
        "ID": 21,
        "track": 3,
        "type": 0,
        "time_begin": 9862,
        "time_end": 0,
        "background": 0
    },
    {
        "ID": 22,
        "track": 2,
        "type": 0,
        "time_begin": 10096,
        "time_end": 0,
        "background": 0
    },
    {
        "ID": 23,
        "track": 3,
        "type": 1,
        "time_begin": 10331,
        "time_end": 10800,
        "background": 0
    },
    {
        "ID": 24,
        "track": 1,
        "type": 0,
        "time_begin": 10800,
        "time_end": 0,
        "background": 0
    },
    {
        "ID": 25,
        "track": 2,
        "type": 0,
        "time_begin": 11268,
        "time_end": 0,
        "background": 0
    },
    {
        "ID": 26,
        "track": 4,
        "type": 0,
        "time_begin": 11268,
        "time_end": 0,
        "background": 0
    },
    {
        "ID": 27,
        "track": 3,
        "type": 0,
        "time_begin": 11503,
        "time_end": 0,
        "background": 0
    },
    {
        "ID": 28,
        "track": 2,
        "type": 0,
        "time_begin": 11737,
        "time_end": 0,
        "background": 0
    },
    {
        "ID": 29,
        "track": 3,
        "type": 0,
        "time_begin": 11971,
        "time_end": 0,
        "background": 0
    },
    {
        "ID": 30,
        "track": 2,
        "type": 1,
        "time_begin": 12206,
        "time_end": 12675,
        "background": 0
    },
    {
        "ID": 31,
        "track": 4,
        "type": 1,
        "time_begin": 12675,
        "time_end": 13143,
        "background": 0
    },
    {
        "ID": 32,
        "track": 1,
        "type": 0,
        "time_begin": 13143,
        "time_end": 0,
        "background": 0
    },
    {
        "ID": 33,
        "track": 3,
        "type": 0,
        "time_begin": 13378,
        "time_end": 0,
        "background": 0
    },
    {
        "ID": 34,
        "track": 1,
        "type": 0,
        "time_begin": 13612,
        "time_end": 0,
        "background": 0
    },
    {
        "ID": 35,
        "track": 3,
        "type": 0,
        "time_begin": 13846,
        "time_end": 0,
        "background": 0
    },
    {
        "ID": 36,
        "track": 1,
        "type": 0,
        "time_begin": 14081,
        "time_end": 0,
        "background": 0
    },
    {
        "ID": 37,
        "track": 4,
        "type": 0,
        "time_begin": 14550,
        "time_end": 0,
        "background": 0
    },
    {
        "ID": 38,
        "track": 1,
        "type": 0,
        "time_begin": 15018,
        "time_end": 0,
        "background": 0
    },
    {
        "ID": 39,
        "track": 3,
        "type": 0,
        "time_begin": 15018,
        "time_end": 0,
        "background": 0
    },
    {
        "ID": 40,
        "track": 2,
        "type": 0,
        "time_begin": 15253,
        "time_end": 0,
        "background": 0
    },
    {
        "ID": 41,
        "track": 3,
        "type": 0,
        "time_begin": 15487,
        "time_end": 0,
        "background": 0
    },
    {
        "ID": 42,
        "track": 2,
        "type": 0,
        "time_begin": 15721,
        "time_end": 0,
        "background": 0
    },
    {
        "ID": 43,
        "track": 4,
        "type": 1,
        "time_begin": 15956,
        "time_end": 16425,
        "background": 0
    },
    {
        "ID": 44,
        "track": 3,
        "type": 0,
        "time_begin": 16425,
        "time_end": 0,
        "background": 0
    },
    {
        "ID": 45,
        "track": 2,
        "type": 0,
        "time_begin": 16659,
        "time_end": 0,
        "background": 0
    },
    {
        "ID": 46,
        "track": 3,
        "type": 0,
        "time_begin": 16893,
        "time_end": 0,
        "background": 0
    },
    {
        "ID": 47,
        "track": 2,
        "type": 0,
        "time_begin": 17128,
        "time_end": 0,
        "background": 0
    },
    {
        "ID": 48,
        "track": 1,
        "type": 0,
        "time_begin": 17362,
        "time_end": 0,
        "background": 0
    },
    {
        "ID": 49,
        "track": 2,
        "type": 0,
        "time_begin": 17596,
        "time_end": 0,
        "background": 0
    },
    {
        "ID": 50,
        "track": 3,
        "type": 1,
        "time_begin": 17831,
        "time_end": 18768,
        "background": 0
    },
    {
        "ID": 51,
        "track": 2,
        "type": 0,
        "time_begin": 18768,
        "time_end": 0,
        "background": 0
    },
    {
        "ID": 52,
        "track": 4,
        "type": 0,
        "time_begin": 18768,
        "time_end": 0,
        "background": 0
    },
    {
        "ID": 53,
        "track": 3,
        "type": 0,
        "time_begin": 19003,
        "time_end": 0,
        "background": 0
    },
    {
        "ID": 54,
        "track": 4,
        "type": 0,
        "time_begin": 19237,
        "time_end": 0,
        "background": 0
    },
    {
        "ID": 55,
        "track": 2,
        "type": 0,
        "time_begin": 19471,
        "time_end": 0,
        "background": 0
    },
    {
        "ID": 56,
        "track": 3,
        "type": 1,
        "time_begin": 19706,
        "time_end": 20175,
        "background": 0
    },
    {
        "ID": 57,
        "track": 2,
        "type": 0,
        "time_begin": 20175,
        "time_end": 0,
        "background": 0
    },
    {
        "ID": 58,
        "track": 3,
        "type": 0,
        "time_begin": 20409,
        "time_end": 0,
        "background": 0
    },
    {
        "ID": 59,
        "track": 1,
        "type": 0,
        "time_begin": 20643,
        "time_end": 0,
        "background": 0
    },
    {
        "ID": 60,
        "track": 4,
        "type": 0,
        "time_begin": 20878,
        "time_end": 0,
        "background": 0
    },
    {
        "ID": 61,
        "track": 1,
        "type": 0,
        "time_begin": 21112,
        "time_end": 0,
        "background": 0
    },
    {
        "ID": 62,
        "track": 4,
        "type": 0,
        "time_begin": 21346,
        "time_end": 0,
        "background": 0
    },
    {
        "ID": 63,
        "track": 1,
        "type": 1,
        "time_begin": 21581,
        "time_end": 22050,
        "background": 0
    },
    {
        "ID": 64,
        "track": 3,
        "type": 1,
        "time_begin": 22050,
        "time_end": 22518,
        "background": 0
    },
    {
        "ID": 65,
        "track": 2,
        "type": 0,
        "time_begin": 22518,
        "time_end": 0,
        "background": 1
    },
    {
        "ID": 66,
        "track": 4,
        "type": 0,
        "time_begin": 22518,
        "time_end": 0,
        "background": 1
    },
    {
        "ID": 67,
        "track": 3,
        "type": 0,
        "time_begin": 22987,
        "time_end": 0,
        "background": 0
    },
    {
        "ID": 68,
        "track": 4,
        "type": 0,
        "time_begin": 23221,
        "time_end": 0,
        "background": 0
    },
    {
        "ID": 69,
        "track": 2,
        "type": 0,
        "time_begin": 23456,
        "time_end": 0,
        "background": 0
    },
    {
        "ID": 70,
        "track": 3,
        "type": 0,
        "time_begin": 23690,
        "time_end": 0,
        "background": 0
    },
    {
        "ID": 71,
        "track": 4,
        "type": 0,
        "time_begin": 23925,
        "time_end": 0,
        "background": 0
    },
    {
        "ID": 72,
        "track": 3,
        "type": 1,
        "time_begin": 24393,
        "time_end": 25331,
        "background": 0
    },
    {
        "ID": 73,
        "track": 1,
        "type": 0,
        "time_begin": 25331,
        "time_end": 0,
        "background": 0
    },
    {
        "ID": 74,
        "track": 3,
        "type": 0,
        "time_begin": 25800,
        "time_end": 0,
        "background": 0
    },
    {
        "ID": 75,
        "track": 2,
        "type": 0,
        "time_begin": 26268,
        "time_end": 0,
        "background": 0
    },
    {
        "ID": 76,
        "track": 4,
        "type": 0,
        "time_begin": 26268,
        "time_end": 0,
        "background": 0
    },
    {
        "ID": 77,
        "track": 3,
        "type": 0,
        "time_begin": 26737,
        "time_end": 0,
        "background": 0
    },
    {
        "ID": 78,
        "track": 2,
        "type": 0,
        "time_begin": 27206,
        "time_end": 0,
        "background": 0
    },
    {
        "ID": 79,
        "track": 1,
        "type": 0,
        "time_begin": 27440,
        "time_end": 0,
        "background": 0
    },
    {
        "ID": 80,
        "track": 2,
        "type": 0,
        "time_begin": 27675,
        "time_end": 0,
        "background": 0
    },
    {
        "ID": 81,
        "track": 1,
        "type": 0,
        "time_begin": 27909,
        "time_end": 0,
        "background": 0
    },
    {
        "ID": 82,
        "track": 3,
        "type": 0,
        "time_begin": 28143,
        "time_end": 0,
        "background": 0
    },
    {
        "ID": 83,
        "track": 2,
        "type": 1,
        "time_begin": 28378,
        "time_end": 29081,
        "background": 0
    },
    {
        "ID": 84,
        "track": 4,
        "type": 0,
        "time_begin": 29081,
        "time_end": 0,
        "background": 0
    },
    {
        "ID": 85,
        "track": 2,
        "type": 0,
        "time_begin": 29550,
        "time_end": 0,
        "background": 0
    },
    {
        "ID": 86,
        "track": 1,
        "type": 0,
        "time_begin": 30018,
        "time_end": 0,
        "background": 0
    },
    {
        "ID": 87,
        "track": 3,
        "type": 0,
        "time_begin": 30018,
        "time_end": 0,
        "background": 0
    },
    {
        "ID": 88,
        "track": 2,
        "type": 0,
        "time_begin": 30487,
        "time_end": 0,
        "background": 0
    },
    {
        "ID": 89,
        "track": 3,
        "type": 0,
        "time_begin": 30956,
        "time_end": 0,
        "background": 0
    },
    {
        "ID": 90,
        "track": 2,
        "type": 0,
        "time_begin": 31190,
        "time_end": 0,
        "background": 0
    },
    {
        "ID": 91,
        "track": 4,
        "type": 0,
        "time_begin": 31425,
        "time_end": 0,
        "background": 0
    },
    {
        "ID": 92,
        "track": 3,
        "type": 0,
        "time_begin": 31893,
        "time_end": 0,
        "background": 0
    },
    {
        "ID": 93,
        "track": 2,
        "type": 1,
        "time_begin": 32128,
        "time_end": 32831,
        "background": 0
    },
    {
        "ID": 94,
        "track": 3,
        "type": 1,
        "time_begin": 32831,
        "time_end": 33768,
        "background": 0
    },
    {
        "ID": 95,
        "track": 2,
        "type": 0,
        "time_begin": 33768,
        "time_end": 0,
        "background": 0
    },
    {
        "ID": 96,
        "track": 4,
        "type": 0,
        "time_begin": 33768,
        "time_end": 0,
        "background": 0
    },
    {
        "ID": 97,
        "track": 3,
        "type": 0,
        "time_begin": 34237,
        "time_end": 0,
        "background": 0
    },
    {
        "ID": 98,
        "track": 2,
        "type": 0,
        "time_begin": 34706,
        "time_end": 0,
        "background": 0
    },
    {
        "ID": 99,
        "track": 4,
        "type": 0,
        "time_begin": 34706,
        "time_end": 0,
        "background": 0
    },
    {
        "ID": 100,
        "track": 3,
        "type": 0,
        "time_begin": 35175,
        "time_end": 0,
        "background": 0
    },
    {
        "ID": 101,
        "track": 2,
        "type": 0,
        "time_begin": 35643,
        "time_end": 0,
        "background": 0
    },
    {
        "ID": 102,
        "track": 1,
        "type": 0,
        "time_begin": 35878,
        "time_end": 0,
        "background": 0
    },
    {
        "ID": 103,
        "track": 3,
        "type": 0,
        "time_begin": 36112,
        "time_end": 0,
        "background": 0
    },
    {
        "ID": 104,
        "track": 2,
        "type": 1,
        "time_begin": 36346,
        "time_end": 37518,
        "background": 0
    },
    {
        "ID": 105,
        "track": 4,
        "type": 1,
        "time_begin": 36346,
        "time_end": 37518,
        "background": 0
    },
    {
        "ID": 106,
        "track": 3,
        "type": 0,
        "time_begin": 37518,
        "time_end": 0,
        "background": 1
    },
    {
        "ID": 107,
        "track": 1,
        "type": 0,
        "time_begin": 37753,
        "time_end": 0,
        "background": 0
    },
    {
        "ID": 108,
        "track": 3,
        "type": 0,
        "time_begin": 37987,
        "time_end": 0,
        "background": 0
    },
    {
        "ID": 109,
        "track": 1,
        "type": 0,
        "time_begin": 38221,
        "time_end": 0,
        "background": 0
    },
    {
        "ID": 110,
        "track": 3,
        "type": 0,
        "time_begin": 38456,
        "time_end": 0,
        "background": 0
    },
    {
        "ID": 111,
        "track": 2,
        "type": 0,
        "time_begin": 38925,
        "time_end": 0,
        "background": 0
    },
    {
        "ID": 112,
        "track": 4,
        "type": 0,
        "time_begin": 39393,
        "time_end": 0,
        "background": 0
    },
    {
        "ID": 113,
        "track": 1,
        "type": 0,
        "time_begin": 39628,
        "time_end": 0,
        "background": 0
    },
    {
        "ID": 114,
        "track": 4,
        "type": 0,
        "time_begin": 39862,
        "time_end": 0,
        "background": 0
    },
    {
        "ID": 115,
        "track": 1,
        "type": 0,
        "time_begin": 40096,
        "time_end": 0,
        "background": 0
    },
    {
        "ID": 116,
        "track": 4,
        "type": 1,
        "time_begin": 40331,
        "time_end": 41268,
        "background": 0
    },
    {
        "ID": 117,
        "track": 1,
        "type": 0,
        "time_begin": 41268,
        "time_end": 0,
        "background": 0
    },
    {
        "ID": 118,
        "track": 3,
        "type": 0,
        "time_begin": 41503,
        "time_end": 0,
        "background": 0
    },
    {
        "ID": 119,
        "track": 1,
        "type": 0,
        "time_begin": 41737,
        "time_end": 0,
        "background": 0
    },
    {
        "ID": 120,
        "track": 4,
        "type": 0,
        "time_begin": 41971,
        "time_end": 0,
        "background": 0
    },
    {
        "ID": 121,
        "track": 2,
        "type": 0,
        "time_begin": 42206,
        "time_end": 0,
        "background": 0
    },
    {
        "ID": 122,
        "track": 3,
        "type": 0,
        "time_begin": 42675,
        "time_end": 0,
        "background": 0
    },
    {
        "ID": 123,
        "track": 4,
        "type": 0,
        "time_begin": 42909,
        "time_end": 0,
        "background": 0
    },
    {
        "ID": 124,
        "track": 1,
        "type": 0,
        "time_begin": 43143,
        "time_end": 0,
        "background": 0
    },
    {
        "ID": 125,
        "track": 3,
        "type": 0,
        "time_begin": 43378,
        "time_end": 0,
        "background": 0
    },
    {
        "ID": 126,
        "track": 2,
        "type": 0,
        "time_begin": 43612,
        "time_end": 0,
        "background": 0
    },
    {
        "ID": 127,
        "track": 4,
        "type": 0,
        "time_begin": 43846,
        "time_end": 0,
        "background": 0
    },
    {
        "ID": 128,
        "track": 3,
        "type": 1,
        "time_begin": 44081,
        "time_end": 45018,
        "background": 0
    },
    {
        "ID": 129,
        "track": 2,
        "type": 0,
        "time_begin": 45018,
        "time_end": 0,
        "background": 0
    },
    {
        "ID": 130,
        "track": 4,
        "type": 0,
        "time_begin": 45018,
        "time_end": 0,
        "background": 0
    },
    {
        "ID": 131,
        "track": 3,
        "type": 0,
        "time_begin": 45487,
        "time_end": 0,
        "background": 0
    },
    {
        "ID": 132,
        "track": 4,
        "type": 0,
        "time_begin": 45721,
        "time_end": 0,
        "background": 0
    },
    {
        "ID": 133,
        "track": 2,
        "type": 0,
        "time_begin": 45956,
        "time_end": 0,
        "background": 0
    },
    {
        "ID": 134,
        "track": 1,
        "type": 0,
        "time_begin": 46190,
        "time_end": 0,
        "background": 0
    },
    {
        "ID": 135,
        "track": 3,
        "type": 0,
        "time_begin": 46425,
        "time_end": 0,
        "background": 0
    },
    {
        "ID": 136,
        "track": 2,
        "type": 0,
        "time_begin": 46893,
        "time_end": 0,
        "background": 0
    },
    {
        "ID": 137,
        "track": 4,
        "type": 0,
        "time_begin": 47128,
        "time_end": 0,
        "background": 0
    },
    {
        "ID": 138,
        "track": 2,
        "type": 0,
        "time_begin": 47362,
        "time_end": 0,
        "background": 0
    },
    {
        "ID": 139,
        "track": 1,
        "type": 0,
        "time_begin": 47596,
        "time_end": 0,
        "background": 0
    },
    {
        "ID": 140,
        "track": 3,
        "type": 1,
        "time_begin": 47831,
        "time_end": 48534,
        "background": 0
    },
    {
        "ID": 141,
        "track": 1,
        "type": 0,
        "time_begin": 48534,
        "time_end": 0,
        "background": 0
    },
    {
        "ID": 142,
        "track": 2,
        "type": 0,
        "time_begin": 48768,
        "time_end": 0,
        "background": 0
    },
    {
        "ID": 143,
        "track": 3,
        "type": 0,
        "time_begin": 49003,
        "time_end": 0,
        "background": 0
    },
    {
        "ID": 144,
        "track": 4,
        "type": 0,
        "time_begin": 49237,
        "time_end": 0,
        "background": 0
    },
    {
        "ID": 145,
        "track": 2,
        "type": 0,
        "time_begin": 49471,
        "time_end": 0,
        "background": 0
    },
    {
        "ID": 146,
        "track": 3,
        "type": 0,
        "time_begin": 49706,
        "time_end": 0,
        "background": 0
    },
    {
        "ID": 147,
        "track": 2,
        "type": 0,
        "time_begin": 50175,
        "time_end": 0,
        "background": 0
    },
    {
        "ID": 148,
        "track": 4,
        "type": 0,
        "time_begin": 50643,
        "time_end": 0,
        "background": 0
    },
    {
        "ID": 149,
        "track": 2,
        "type": 0,
        "time_begin": 51112,
        "time_end": 0,
        "background": 0
    },
    {
        "ID": 150,
        "track": 1,
        "type": 1,
        "time_begin": 51581,
        "time_end": 52518,
        "background": 0
    },
    {
        "ID": 151,
        "track": 3,
        "type": 1,
        "time_begin": 51581,
        "time_end": 52518,
        "background": 0
    },
    {
        "ID": 152,
        "track": 2,
        "type": 1,
        "time_begin": 52518,
        "time_end": 53456,
        "background": 1
    },
    {
        "ID": 153,
        "track": 3,
        "type": 0,
        "time_begin": 53456,
        "time_end": 0,
        "background": 0
    },
    {
        "ID": 154,
        "track": 4,
        "type": 0,
        "time_begin": 53690,
        "time_end": 0,
        "background": 0
    },
    {
        "ID": 155,
        "track": 3,
        "type": 0,
        "time_begin": 53925,
        "time_end": 0,
        "background": 0
    },
    {
        "ID": 156,
        "track": 4,
        "type": 1,
        "time_begin": 54393,
        "time_end": 55331,
        "background": 0
    },
    {
        "ID": 157,
        "track": 3,
        "type": 0,
        "time_begin": 55331,
        "time_end": 0,
        "background": 0
    },
    {
        "ID": 158,
        "track": 2,
        "type": 0,
        "time_begin": 55565,
        "time_end": 0,
        "background": 0
    },
    {
        "ID": 159,
        "track": 3,
        "type": 0,
        "time_begin": 55800,
        "time_end": 0,
        "background": 0
    },
    {
        "ID": 160,
        "track": 1,
        "type": 1,
        "time_begin": 56268,
        "time_end": 57206,
        "background": 0
    },
    {
        "ID": 161,
        "track": 2,
        "type": 0,
        "time_begin": 57206,
        "time_end": 0,
        "background": 0
    },
    {
        "ID": 162,
        "track": 3,
        "type": 0,
        "time_begin": 57440,
        "time_end": 0,
        "background": 0
    },
    {
        "ID": 163,
        "track": 2,
        "type": 0,
        "time_begin": 57675,
        "time_end": 0,
        "background": 0
    },
    {
        "ID": 164,
        "track": 4,
        "type": 0,
        "time_begin": 58143,
        "time_end": 0,
        "background": 0
    },
    {
        "ID": 165,
        "track": 3,
        "type": 0,
        "time_begin": 58378,
        "time_end": 0,
        "background": 0
    },
    {
        "ID": 166,
        "track": 4,
        "type": 0,
        "time_begin": 58612,
        "time_end": 0,
        "background": 0
    },
    {
        "ID": 167,
        "track": 3,
        "type": 0,
        "time_begin": 58846,
        "time_end": 0,
        "background": 0
    },
    {
        "ID": 168,
        "track": 1,
        "type": 0,
        "time_begin": 59081,
        "time_end": 0,
        "background": 0
    },
    {
        "ID": 169,
        "track": 2,
        "type": 0,
        "time_begin": 59315,
        "time_end": 0,
        "background": 0
    },
    {
        "ID": 170,
        "track": 1,
        "type": 0,
        "time_begin": 59550,
        "time_end": 0,
        "background": 0
    },
    {
        "ID": 171,
        "track": 3,
        "type": 1,
        "time_begin": 60018,
        "time_end": 60956,
        "background": 0
    },
    {
        "ID": 172,
        "track": 1,
        "type": 0,
        "time_begin": 60956,
        "time_end": 0,
        "background": 0
    },
    {
        "ID": 173,
        "track": 4,
        "type": 0,
        "time_begin": 61190,
        "time_end": 0,
        "background": 0
    },
    {
        "ID": 174,
        "track": 1,
        "type": 0,
        "time_begin": 61425,
        "time_end": 0,
        "background": 0
    },
    {
        "ID": 175,
        "track": 3,
        "type": 1,
        "time_begin": 61893,
        "time_end": 62831,
        "background": 0
    },
    {
        "ID": 176,
        "track": 4,
        "type": 0,
        "time_begin": 62831,
        "time_end": 0,
        "background": 0
    },
    {
        "ID": 177,
        "track": 3,
        "type": 0,
        "time_begin": 63065,
        "time_end": 0,
        "background": 0
    },
    {
        "ID": 178,
        "track": 2,
        "type": 0,
        "time_begin": 63300,
        "time_end": 0,
        "background": 0
    },
    {
        "ID": 179,
        "track": 1,
        "type": 1,
        "time_begin": 63768,
        "time_end": 64706,
        "background": 0
    },
    {
        "ID": 180,
        "track": 4,
        "type": 0,
        "time_begin": 64706,
        "time_end": 0,
        "background": 0
    },
    {
        "ID": 181,
        "track": 2,
        "type": 0,
        "time_begin": 64940,
        "time_end": 0,
        "background": 0
    },
    {
        "ID": 182,
        "track": 4,
        "type": 0,
        "time_begin": 65175,
        "time_end": 0,
        "background": 0
    },
    {
        "ID": 183,
        "track": 3,
        "type": 0,
        "time_begin": 65643,
        "time_end": 0,
        "background": 0
    },
    {
        "ID": 184,
        "track": 2,
        "type": 0,
        "time_begin": 65878,
        "time_end": 0,
        "background": 0
    },
    {
        "ID": 185,
        "track": 3,
        "type": 0,
        "time_begin": 66112,
        "time_end": 0,
        "background": 0
    },
    {
        "ID": 186,
        "track": 1,
        "type": 0,
        "time_begin": 66346,
        "time_end": 0,
        "background": 0
    },
    {
        "ID": 187,
        "track": 3,
        "type": 0,
        "time_begin": 66581,
        "time_end": 0,
        "background": 0
    },
    {
        "ID": 188,
        "track": 2,
        "type": 0,
        "time_begin": 66815,
        "time_end": 0,
        "background": 0
    },
    {
        "ID": 189,
        "track": 3,
        "type": 0,
        "time_begin": 67050,
        "time_end": 0,
        "background": 0
    }
]
