[{"ID": 1, "track": 1, "type": 1, "time_begin": 516, "time_end": 1079, "background": 0}, {"ID": 2, "track": 3, "type": 0, "time_begin": 1079, "time_end": 0, "background": 0}, {"ID": 3, "track": 4, "type": 0, "time_begin": 1266, "time_end": 0, "background": 0}, {"ID": 4, "track": 2, "type": 0, "time_begin": 1266, "time_end": 0, "background": 0}, {"ID": 5, "track": 3, "type": 0, "time_begin": 1454, "time_end": 0, "background": 0}, {"ID": 6, "track": 2, "type": 0, "time_begin": 1641, "time_end": 0, "background": 0}, {"ID": 7, "track": 4, "type": 0, "time_begin": 1829, "time_end": 0, "background": 0}, {"ID": 8, "track": 3, "type": 0, "time_begin": 2016, "time_end": 0, "background": 0}, {"ID": 9, "track": 1, "type": 0, "time_begin": 2016, "time_end": 0, "background": 0}, {"ID": 10, "track": 2, "type": 0, "time_begin": 2391, "time_end": 0, "background": 0}, {"ID": 11, "track": 3, "type": 0, "time_begin": 2766, "time_end": 0, "background": 0}, {"ID": 12, "track": 1, "type": 0, "time_begin": 2766, "time_end": 0, "background": 0}, {"ID": 13, "track": 2, "type": 0, "time_begin": 3141, "time_end": 0, "background": 0}, {"ID": 14, "track": 3, "type": 0, "time_begin": 3329, "time_end": 0, "background": 0}, {"ID": 15, "track": 2, "type": 1, "time_begin": 3516, "time_end": 4079, "background": 0}, {"ID": 16, "track": 4, "type": 1, "time_begin": 3516, "time_end": 4079, "background": 0}, {"ID": 17, "track": 3, "type": 0, "time_begin": 4079, "time_end": 0, "background": 0}, {"ID": 18, "track": 1, "type": 0, "time_begin": 4266, "time_end": 0, "background": 0}, {"ID": 19, "track": 3, "type": 0, "time_begin": 4454, "time_end": 0, "background": 0}, {"ID": 20, "track": 2, "type": 0, "time_begin": 4641, "time_end": 0, "background": 0}, {"ID": 21, "track": 4, "type": 0, "time_begin": 4829, "time_end": 0, "background": 0}, {"ID": 22, "track": 1, "type": 1, "time_begin": 5016, "time_end": 5391, "background": 0}, {"ID": 23, "track": 2, "type": 1, "time_begin": 5391, "time_end": 5766, "background": 0}, {"ID": 24, "track": 3, "type": 1, "time_begin": 5766, "time_end": 6516, "background": 0}, {"ID": 25, "track": 1, "type": 1, "time_begin": 6516, "time_end": 7079, "background": 0}, {"ID": 26, "track": 3, "type": 0, "time_begin": 7079, "time_end": 0, "background": 0}, {"ID": 27, "track": 4, "type": 0, "time_begin": 7266, "time_end": 0, "background": 0}, {"ID": 28, "track": 2, "type": 0, "time_begin": 7454, "time_end": 0, "background": 0}, {"ID": 29, "track": 4, "type": 0, "time_begin": 7641, "time_end": 0, "background": 0}, {"ID": 30, "track": 3, "type": 0, "time_begin": 7829, "time_end": 0, "background": 0}, {"ID": 31, "track": 1, "type": 1, "time_begin": 8016, "time_end": 8391, "background": 0}, {"ID": 32, "track": 3, "type": 1, "time_begin": 8391, "time_end": 8766, "background": 0}, {"ID": 33, "track": 2, "type": 1, "time_begin": 8766, "time_end": 9141, "background": 0}, {"ID": 34, "track": 4, "type": 0, "time_begin": 9141, "time_end": 0, "background": 0}, {"ID": 35, "track": 3, "type": 0, "time_begin": 9329, "time_end": 0, "background": 0}, {"ID": 36, "track": 4, "type": 1, "time_begin": 9516, "time_end": 10079, "background": 0}, {"ID": 37, "track": 2, "type": 0, "time_begin": 10079, "time_end": 0, "background": 0}, {"ID": 38, "track": 3, "type": 0, "time_begin": 10266, "time_end": 0, "background": 0}, {"ID": 39, "track": 1, "type": 0, "time_begin": 10454, "time_end": 0, "background": 0}, {"ID": 40, "track": 4, "type": 0, "time_begin": 10641, "time_end": 0, "background": 0}, {"ID": 41, "track": 3, "type": 0, "time_begin": 10829, "time_end": 0, "background": 0}, {"ID": 42, "track": 2, "type": 0, "time_begin": 11016, "time_end": 0, "background": 0}, {"ID": 43, "track": 4, "type": 0, "time_begin": 11016, "time_end": 0, "background": 0}, {"ID": 44, "track": 3, "type": 0, "time_begin": 11391, "time_end": 0, "background": 0}, {"ID": 45, "track": 1, "type": 0, "time_begin": 11391, "time_end": 0, "background": 0}, {"ID": 46, "track": 4, "type": 0, "time_begin": 11766, "time_end": 0, "background": 0}, {"ID": 47, "track": 2, "type": 0, "time_begin": 11766, "time_end": 0, "background": 0}, {"ID": 48, "track": 3, "type": 0, "time_begin": 12141, "time_end": 0, "background": 0}, {"ID": 49, "track": 4, "type": 0, "time_begin": 12329, "time_end": 0, "background": 0}, {"ID": 50, "track": 3, "type": 0, "time_begin": 12516, "time_end": 0, "background": 1}, {"ID": 51, "track": 1, "type": 0, "time_begin": 12704, "time_end": 0, "background": 0}, {"ID": 52, "track": 3, "type": 0, "time_begin": 12891, "time_end": 0, "background": 0}, {"ID": 53, "track": 2, "type": 0, "time_begin": 13079, "time_end": 0, "background": 0}, {"ID": 54, "track": 4, "type": 0, "time_begin": 13266, "time_end": 0, "background": 0}, {"ID": 55, "track": 3, "type": 1, "time_begin": 13454, "time_end": 13829, "background": 0}, {"ID": 56, "track": 4, "type": 0, "time_begin": 13829, "time_end": 0, "background": 0}, {"ID": 57, "track": 2, "type": 1, "time_begin": 14016, "time_end": 14391, "background": 0}, {"ID": 58, "track": 1, "type": 0, "time_begin": 14391, "time_end": 0, "background": 0}, {"ID": 59, "track": 4, "type": 0, "time_begin": 14579, "time_end": 0, "background": 0}, {"ID": 60, "track": 2, "type": 0, "time_begin": 14766, "time_end": 0, "background": 0}, {"ID": 61, "track": 4, "type": 1, "time_begin": 14954, "time_end": 15329, "background": 0}, {"ID": 62, "track": 2, "type": 0, "time_begin": 15329, "time_end": 0, "background": 0}, {"ID": 63, "track": 3, "type": 0, "time_begin": 15516, "time_end": 0, "background": 0}, {"ID": 64, "track": 1, "type": 0, "time_begin": 15704, "time_end": 0, "background": 0}, {"ID": 65, "track": 3, "type": 0, "time_begin": 15891, "time_end": 0, "background": 0}, {"ID": 66, "track": 2, "type": 0, "time_begin": 16079, "time_end": 0, "background": 0}, {"ID": 67, "track": 4, "type": 0, "time_begin": 16266, "time_end": 0, "background": 0}, {"ID": 68, "track": 3, "type": 1, "time_begin": 16454, "time_end": 16829, "background": 0}, {"ID": 69, "track": 1, "type": 0, "time_begin": 16829, "time_end": 0, "background": 0}, {"ID": 70, "track": 3, "type": 0, "time_begin": 17016, "time_end": 0, "background": 0}, {"ID": 71, "track": 2, "type": 0, "time_begin": 17204, "time_end": 0, "background": 0}, {"ID": 72, "track": 4, "type": 0, "time_begin": 17391, "time_end": 0, "background": 0}, {"ID": 73, "track": 3, "type": 0, "time_begin": 17579, "time_end": 0, "background": 0}, {"ID": 74, "track": 2, "type": 1, "time_begin": 17766, "time_end": 18141, "background": 0}, {"ID": 75, "track": 1, "type": 1, "time_begin": 18141, "time_end": 18516, "background": 0}, {"ID": 76, "track": 3, "type": 0, "time_begin": 18516, "time_end": 0, "background": 0}, {"ID": 77, "track": 4, "type": 0, "time_begin": 18704, "time_end": 0, "background": 0}, {"ID": 78, "track": 3, "type": 0, "time_begin": 18891, "time_end": 0, "background": 0}, {"ID": 79, "track": 2, "type": 0, "time_begin": 19079, "time_end": 0, "background": 0}, {"ID": 80, "track": 4, "type": 0, "time_begin": 19266, "time_end": 0, "background": 0}, {"ID": 81, "track": 3, "type": 1, "time_begin": 19454, "time_end": 19829, "background": 0}, {"ID": 82, "track": 2, "type": 0, "time_begin": 19829, "time_end": 0, "background": 0}, {"ID": 83, "track": 1, "type": 1, "time_begin": 20016, "time_end": 20391, "background": 0}, {"ID": 84, "track": 4, "type": 0, "time_begin": 20391, "time_end": 0, "background": 0}, {"ID": 85, "track": 3, "type": 0, "time_begin": 20579, "time_end": 0, "background": 0}, {"ID": 86, "track": 2, "type": 0, "time_begin": 20766, "time_end": 0, "background": 0}, {"ID": 87, "track": 3, "type": 1, "time_begin": 20954, "time_end": 21329, "background": 0}, {"ID": 88, "track": 1, "type": 0, "time_begin": 21329, "time_end": 0, "background": 0}, {"ID": 89, "track": 4, "type": 0, "time_begin": 21516, "time_end": 0, "background": 0}, {"ID": 90, "track": 2, "type": 0, "time_begin": 21704, "time_end": 0, "background": 0}, {"ID": 91, "track": 3, "type": 0, "time_begin": 21891, "time_end": 0, "background": 0}, {"ID": 92, "track": 1, "type": 0, "time_begin": 22079, "time_end": 0, "background": 0}, {"ID": 93, "track": 4, "type": 0, "time_begin": 22266, "time_end": 0, "background": 0}, {"ID": 94, "track": 2, "type": 1, "time_begin": 22454, "time_end": 22829, "background": 0}, {"ID": 95, "track": 1, "type": 0, "time_begin": 22829, "time_end": 0, "background": 0}, {"ID": 96, "track": 4, "type": 0, "time_begin": 23016, "time_end": 0, "background": 0}, {"ID": 97, "track": 2, "type": 0, "time_begin": 23204, "time_end": 0, "background": 0}, {"ID": 98, "track": 3, "type": 0, "time_begin": 23391, "time_end": 0, "background": 0}, {"ID": 99, "track": 1, "type": 0, "time_begin": 23579, "time_end": 0, "background": 0}, {"ID": 100, "track": 2, "type": 1, "time_begin": 23766, "time_end": 24516, "background": 0}, {"ID": 101, "track": 4, "type": 1, "time_begin": 23766, "time_end": 24516, "background": 0}, {"ID": 102, "track": 3, "type": 0, "time_begin": 24516, "time_end": 0, "background": 1}, {"ID": 103, "track": 1, "type": 0, "time_begin": 24704, "time_end": 0, "background": 0}, {"ID": 104, "track": 3, "type": 0, "time_begin": 24891, "time_end": 0, "background": 0}, {"ID": 105, "track": 2, "type": 0, "time_begin": 25079, "time_end": 0, "background": 0}, {"ID": 106, "track": 4, "type": 0, "time_begin": 25266, "time_end": 0, "background": 0}, {"ID": 107, "track": 3, "type": 0, "time_begin": 25454, "time_end": 0, "background": 0}, {"ID": 108, "track": 2, "type": 0, "time_begin": 25641, "time_end": 0, "background": 0}, {"ID": 109, "track": 3, "type": 0, "time_begin": 25829, "time_end": 0, "background": 0}, {"ID": 110, "track": 1, "type": 1, "time_begin": 26016, "time_end": 26391, "background": 0}, {"ID": 111, "track": 2, "type": 0, "time_begin": 26391, "time_end": 0, "background": 0}, {"ID": 112, "track": 4, "type": 0, "time_begin": 26391, "time_end": 0, "background": 0}, {"ID": 113, "track": 3, "type": 1, "time_begin": 26579, "time_end": 26954, "background": 0}, {"ID": 114, "track": 2, "type": 0, "time_begin": 26954, "time_end": 0, "background": 0}, {"ID": 115, "track": 1, "type": 0, "time_begin": 27141, "time_end": 0, "background": 0}, {"ID": 116, "track": 3, "type": 0, "time_begin": 27141, "time_end": 0, "background": 0}, {"ID": 117, "track": 2, "type": 0, "time_begin": 27329, "time_end": 0, "background": 0}, {"ID": 118, "track": 4, "type": 0, "time_begin": 27516, "time_end": 0, "background": 0}, {"ID": 119, "track": 2, "type": 0, "time_begin": 27704, "time_end": 0, "background": 0}, {"ID": 120, "track": 3, "type": 0, "time_begin": 27891, "time_end": 0, "background": 0}, {"ID": 121, "track": 1, "type": 0, "time_begin": 28079, "time_end": 0, "background": 0}, {"ID": 122, "track": 3, "type": 0, "time_begin": 28266, "time_end": 0, "background": 0}, {"ID": 123, "track": 2, "type": 0, "time_begin": 28454, "time_end": 0, "background": 0}, {"ID": 124, "track": 4, "type": 1, "time_begin": 28641, "time_end": 29016, "background": 0}, {"ID": 125, "track": 2, "type": 1, "time_begin": 29016, "time_end": 29391, "background": 0}, {"ID": 126, "track": 1, "type": 0, "time_begin": 29391, "time_end": 0, "background": 0}, {"ID": 127, "track": 3, "type": 0, "time_begin": 29391, "time_end": 0, "background": 0}, {"ID": 128, "track": 2, "type": 1, "time_begin": 29579, "time_end": 29954, "background": 0}, {"ID": 129, "track": 3, "type": 0, "time_begin": 29954, "time_end": 0, "background": 0}, {"ID": 130, "track": 2, "type": 0, "time_begin": 30141, "time_end": 0, "background": 0}, {"ID": 131, "track": 4, "type": 0, "time_begin": 30141, "time_end": 0, "background": 0}, {"ID": 132, "track": 3, "type": 0, "time_begin": 30329, "time_end": 0, "background": 0}, {"ID": 133, "track": 2, "type": 0, "time_begin": 30516, "time_end": 0, "background": 0}, {"ID": 134, "track": 3, "type": 0, "time_begin": 30704, "time_end": 0, "background": 0}, {"ID": 135, "track": 1, "type": 0, "time_begin": 30891, "time_end": 0, "background": 0}, {"ID": 136, "track": 3, "type": 0, "time_begin": 31079, "time_end": 0, "background": 0}, {"ID": 137, "track": 2, "type": 0, "time_begin": 31266, "time_end": 0, "background": 0}, {"ID": 138, "track": 4, "type": 0, "time_begin": 31454, "time_end": 0, "background": 0}, {"ID": 139, "track": 3, "type": 0, "time_begin": 31641, "time_end": 0, "background": 0}, {"ID": 140, "track": 2, "type": 0, "time_begin": 31829, "time_end": 0, "background": 0}, {"ID": 141, "track": 1, "type": 1, "time_begin": 32016, "time_end": 32391, "background": 0}, {"ID": 142, "track": 2, "type": 1, "time_begin": 32391, "time_end": 32766, "background": 0}, {"ID": 143, "track": 3, "type": 1, "time_begin": 32766, "time_end": 33141, "background": 0}, {"ID": 144, "track": 4, "type": 1, "time_begin": 33141, "time_end": 33516, "background": 0}, {"ID": 145, "track": 1, "type": 1, "time_begin": 33516, "time_end": 34641, "background": 0}, {"ID": 146, "track": 2, "type": 0, "time_begin": 34641, "time_end": 0, "background": 0}, {"ID": 147, "track": 3, "type": 0, "time_begin": 34829, "time_end": 0, "background": 0}, {"ID": 148, "track": 2, "type": 0, "time_begin": 35016, "time_end": 0, "background": 0}, {"ID": 149, "track": 4, "type": 0, "time_begin": 35204, "time_end": 0, "background": 0}, {"ID": 150, "track": 3, "type": 0, "time_begin": 35391, "time_end": 0, "background": 0}, {"ID": 151, "track": 4, "type": 1, "time_begin": 35579, "time_end": 36141, "background": 0}, {"ID": 152, "track": 1, "type": 0, "time_begin": 36141, "time_end": 0, "background": 0}, {"ID": 153, "track": 2, "type": 0, "time_begin": 36329, "time_end": 0, "background": 0}, {"ID": 154, "track": 1, "type": 0, "time_begin": 36516, "time_end": 0, "background": 0}, {"ID": 155, "track": 3, "type": 0, "time_begin": 36704, "time_end": 0, "background": 0}, {"ID": 156, "track": 2, "type": 0, "time_begin": 36891, "time_end": 0, "background": 0}, {"ID": 157, "track": 4, "type": 1, "time_begin": 37079, "time_end": 37641, "background": 0}, {"ID": 158, "track": 2, "type": 0, "time_begin": 37641, "time_end": 0, "background": 0}, {"ID": 159, "track": 3, "type": 0, "time_begin": 37829, "time_end": 0, "background": 0}, {"ID": 160, "track": 1, "type": 0, "time_begin": 38016, "time_end": 0, "background": 0}, {"ID": 161, "track": 2, "type": 0, "time_begin": 38204, "time_end": 0, "background": 0}, {"ID": 162, "track": 1, "type": 0, "time_begin": 38391, "time_end": 0, "background": 0}, {"ID": 163, "track": 2, "type": 1, "time_begin": 38579, "time_end": 39141, "background": 0}, {"ID": 164, "track": 4, "type": 0, "time_begin": 39141, "time_end": 0, "background": 0}, {"ID": 165, "track": 3, "type": 0, "time_begin": 39329, "time_end": 0, "background": 0}, {"ID": 166, "track": 4, "type": 1, "time_begin": 39516, "time_end": 39891, "background": 0}, {"ID": 167, "track": 1, "type": 1, "time_begin": 39891, "time_end": 40266, "background": 0}, {"ID": 168, "track": 4, "type": 1, "time_begin": 40266, "time_end": 40641, "background": 0}, {"ID": 169, "track": 1, "type": 1, "time_begin": 40641, "time_end": 41016, "background": 0}, {"ID": 170, "track": 2, "type": 1, "time_begin": 41016, "time_end": 42516, "background": 0}, {"ID": 171, "track": 4, "type": 1, "time_begin": 41016, "time_end": 42516, "background": 0}, {"ID": 172, "track": 1, "type": 1, "time_begin": 42516, "time_end": 43079, "background": 1}, {"ID": 173, "track": 3, "type": 1, "time_begin": 42516, "time_end": 43079, "background": 1}, {"ID": 174, "track": 2, "type": 0, "time_begin": 43079, "time_end": 0, "background": 0}, {"ID": 175, "track": 3, "type": 0, "time_begin": 43266, "time_end": 0, "background": 0}, {"ID": 176, "track": 2, "type": 0, "time_begin": 43454, "time_end": 0, "background": 0}, {"ID": 177, "track": 4, "type": 0, "time_begin": 43641, "time_end": 0, "background": 0}, {"ID": 178, "track": 3, "type": 0, "time_begin": 43829, "time_end": 0, "background": 0}, {"ID": 179, "track": 1, "type": 1, "time_begin": 44016, "time_end": 44391, "background": 0}, {"ID": 180, "track": 2, "type": 1, "time_begin": 44391, "time_end": 44766, "background": 0}, {"ID": 181, "track": 3, "type": 1, "time_begin": 44766, "time_end": 45141, "background": 0}, {"ID": 182, "track": 4, "type": 0, "time_begin": 45141, "time_end": 0, "background": 0}, {"ID": 183, "track": 3, "type": 0, "time_begin": 45329, "time_end": 0, "background": 0}, {"ID": 184, "track": 2, "type": 1, "time_begin": 45516, "time_end": 46079, "background": 0}, {"ID": 185, "track": 1, "type": 0, "time_begin": 46079, "time_end": 0, "background": 0}, {"ID": 186, "track": 3, "type": 0, "time_begin": 46266, "time_end": 0, "background": 0}, {"ID": 187, "track": 2, "type": 0, "time_begin": 46454, "time_end": 0, "background": 0}, {"ID": 188, "track": 3, "type": 0, "time_begin": 46641, "time_end": 0, "background": 0}, {"ID": 189, "track": 4, "type": 0, "time_begin": 46829, "time_end": 0, "background": 0}, {"ID": 190, "track": 1, "type": 1, "time_begin": 47016, "time_end": 47391, "background": 0}, {"ID": 191, "track": 2, "type": 1, "time_begin": 47391, "time_end": 47766, "background": 0}, {"ID": 192, "track": 3, "type": 1, "time_begin": 47766, "time_end": 48516, "background": 0}, {"ID": 193, "track": 2, "type": 1, "time_begin": 48516, "time_end": 49079, "background": 0}, {"ID": 194, "track": 4, "type": 1, "time_begin": 48516, "time_end": 49079, "background": 0}, {"ID": 195, "track": 1, "type": 0, "time_begin": 49079, "time_end": 0, "background": 0}, {"ID": 196, "track": 3, "type": 0, "time_begin": 49266, "time_end": 0, "background": 0}, {"ID": 197, "track": 2, "type": 0, "time_begin": 49454, "time_end": 0, "background": 0}, {"ID": 198, "track": 4, "type": 0, "time_begin": 49641, "time_end": 0, "background": 0}, {"ID": 199, "track": 3, "type": 0, "time_begin": 49829, "time_end": 0, "background": 0}, {"ID": 200, "track": 1, "type": 1, "time_begin": 50016, "time_end": 50391, "background": 0}, {"ID": 201, "track": 2, "type": 1, "time_begin": 50391, "time_end": 50766, "background": 0}, {"ID": 202, "track": 3, "type": 1, "time_begin": 50766, "time_end": 51141, "background": 0}, {"ID": 203, "track": 4, "type": 0, "time_begin": 51141, "time_end": 0, "background": 0}, {"ID": 204, "track": 3, "type": 0, "time_begin": 51329, "time_end": 0, "background": 0}, {"ID": 205, "track": 4, "type": 1, "time_begin": 51516, "time_end": 52079, "background": 0}, {"ID": 206, "track": 3, "type": 0, "time_begin": 52079, "time_end": 0, "background": 0}, {"ID": 207, "track": 2, "type": 0, "time_begin": 52266, "time_end": 0, "background": 0}, {"ID": 208, "track": 1, "type": 0, "time_begin": 52454, "time_end": 0, "background": 0}, {"ID": 209, "track": 3, "type": 0, "time_begin": 52641, "time_end": 0, "background": 0}, {"ID": 210, "track": 2, "type": 0, "time_begin": 52829, "time_end": 0, "background": 0}, {"ID": 211, "track": 4, "type": 1, "time_begin": 53016, "time_end": 53391, "background": 0}, {"ID": 212, "track": 3, "type": 1, "time_begin": 53391, "time_end": 53766, "background": 0}, {"ID": 213, "track": 2, "type": 1, "time_begin": 53766, "time_end": 54516, "background": 0}, {"ID": 214, "track": 1, "type": 1, "time_begin": 54516, "time_end": 55079, "background": 1}, {"ID": 215, "track": 3, "type": 1, "time_begin": 54516, "time_end": 55079, "background": 1}, {"ID": 216, "track": 2, "type": 0, "time_begin": 55079, "time_end": 0, "background": 0}, {"ID": 217, "track": 4, "type": 0, "time_begin": 55266, "time_end": 0, "background": 0}, {"ID": 218, "track": 2, "type": 0, "time_begin": 55454, "time_end": 0, "background": 0}, {"ID": 219, "track": 3, "type": 0, "time_begin": 55641, "time_end": 0, "background": 0}, {"ID": 220, "track": 1, "type": 0, "time_begin": 55829, "time_end": 0, "background": 0}, {"ID": 221, "track": 4, "type": 1, "time_begin": 56016, "time_end": 56391, "background": 0}, {"ID": 222, "track": 3, "type": 1, "time_begin": 56391, "time_end": 56766, "background": 0}, {"ID": 223, "track": 2, "type": 1, "time_begin": 56766, "time_end": 57141, "background": 0}, {"ID": 224, "track": 1, "type": 0, "time_begin": 57141, "time_end": 0, "background": 0}, {"ID": 225, "track": 3, "type": 0, "time_begin": 57329, "time_end": 0, "background": 0}, {"ID": 226, "track": 2, "type": 1, "time_begin": 57516, "time_end": 58079, "background": 0}, {"ID": 227, "track": 4, "type": 0, "time_begin": 58079, "time_end": 0, "background": 0}, {"ID": 228, "track": 3, "type": 0, "time_begin": 58266, "time_end": 0, "background": 0}, {"ID": 229, "track": 2, "type": 0, "time_begin": 58454, "time_end": 0, "background": 0}, {"ID": 230, "track": 3, "type": 0, "time_begin": 58641, "time_end": 0, "background": 0}, {"ID": 231, "track": 1, "type": 0, "time_begin": 58829, "time_end": 0, "background": 0}, {"ID": 232, "track": 2, "type": 1, "time_begin": 59016, "time_end": 59391, "background": 0}, {"ID": 233, "track": 3, "type": 1, "time_begin": 59391, "time_end": 59766, "background": 0}, {"ID": 234, "track": 4, "type": 1, "time_begin": 59766, "time_end": 60516, "background": 0}, {"ID": 235, "track": 1, "type": 1, "time_begin": 60516, "time_end": 61079, "background": 0}, {"ID": 236, "track": 3, "type": 1, "time_begin": 60516, "time_end": 61079, "background": 0}, {"ID": 237, "track": 2, "type": 0, "time_begin": 61079, "time_end": 0, "background": 0}, {"ID": 238, "track": 3, "type": 0, "time_begin": 61266, "time_end": 0, "background": 0}, {"ID": 239, "track": 1, "type": 0, "time_begin": 61454, "time_end": 0, "background": 0}, {"ID": 240, "track": 3, "type": 0, "time_begin": 61641, "time_end": 0, "background": 0}, {"ID": 241, "track": 4, "type": 0, "time_begin": 61829, "time_end": 0, "background": 0}, {"ID": 242, "track": 1, "type": 1, "time_begin": 62016, "time_end": 62391, "background": 0}, {"ID": 243, "track": 2, "type": 1, "time_begin": 62391, "time_end": 62766, "background": 0}, {"ID": 244, "track": 3, "type": 1, "time_begin": 62766, "time_end": 63141, "background": 0}, {"ID": 245, "track": 4, "type": 0, "time_begin": 63141, "time_end": 0, "background": 0}, {"ID": 246, "track": 2, "type": 0, "time_begin": 63329, "time_end": 0, "background": 0}, {"ID": 247, "track": 3, "type": 1, "time_begin": 63516, "time_end": 64079, "background": 0}, {"ID": 248, "track": 1, "type": 0, "time_begin": 64079, "time_end": 0, "background": 0}, {"ID": 249, "track": 3, "type": 0, "time_begin": 64266, "time_end": 0, "background": 0}, {"ID": 250, "track": 2, "type": 0, "time_begin": 64454, "time_end": 0, "background": 0}, {"ID": 251, "track": 4, "type": 0, "time_begin": 64641, "time_end": 0, "background": 0}, {"ID": 252, "track": 3, "type": 0, "time_begin": 64829, "time_end": 0, "background": 0}, {"ID": 253, "track": 2, "type": 1, "time_begin": 65016, "time_end": 65391, "background": 0}, {"ID": 254, "track": 1, "type": 1, "time_begin": 65391, "time_end": 65766, "background": 0}, {"ID": 255, "track": 3, "type": 1, "time_begin": 65766, "time_end": 66141, "background": 0}, {"ID": 256, "track": 4, "type": 0, "time_begin": 66141, "time_end": 0, "background": 0}, {"ID": 257, "track": 2, "type": 0, "time_begin": 66329, "time_end": 0, "background": 0}, {"ID": 258, "track": 3, "type": 1, "time_begin": 66516, "time_end": 67079, "background": 0}, {"ID": 259, "track": 1, "type": 0, "time_begin": 67079, "time_end": 0, "background": 0}, {"ID": 260, "track": 3, "type": 0, "time_begin": 67266, "time_end": 0, "background": 0}, {"ID": 261, "track": 2, "type": 0, "time_begin": 67454, "time_end": 0, "background": 0}, {"ID": 262, "track": 4, "type": 0, "time_begin": 67641, "time_end": 0, "background": 0}, {"ID": 263, "track": 3, "type": 0, "time_begin": 67829, "time_end": 0, "background": 0}, {"ID": 264, "track": 2, "type": 0, "time_begin": 68016, "time_end": 0, "background": 0}, {"ID": 265, "track": 4, "type": 0, "time_begin": 68016, "time_end": 0, "background": 0}, {"ID": 266, "track": 1, "type": 0, "time_begin": 68391, "time_end": 0, "background": 0}, {"ID": 267, "track": 3, "type": 0, "time_begin": 68391, "time_end": 0, "background": 0}, {"ID": 268, "track": 2, "type": 0, "time_begin": 68766, "time_end": 0, "background": 0}, {"ID": 269, "track": 4, "type": 0, "time_begin": 68766, "time_end": 0, "background": 0}, {"ID": 270, "track": 1, "type": 1, "time_begin": 69516, "time_end": 70079, "background": 1}, {"ID": 271, "track": 3, "type": 1, "time_begin": 69516, "time_end": 70079, "background": 1}, {"ID": 272, "track": 2, "type": 0, "time_begin": 70079, "time_end": 0, "background": 0}, {"ID": 273, "track": 3, "type": 0, "time_begin": 70266, "time_end": 0, "background": 0}, {"ID": 274, "track": 2, "type": 0, "time_begin": 70454, "time_end": 0, "background": 0}, {"ID": 275, "track": 4, "type": 0, "time_begin": 70641, "time_end": 0, "background": 0}, {"ID": 276, "track": 3, "type": 0, "time_begin": 70829, "time_end": 0, "background": 0}, {"ID": 277, "track": 1, "type": 1, "time_begin": 71016, "time_end": 71391, "background": 0}, {"ID": 278, "track": 3, "type": 1, "time_begin": 71391, "time_end": 71766, "background": 0}, {"ID": 279, "track": 4, "type": 1, "time_begin": 71766, "time_end": 72141, "background": 0}, {"ID": 280, "track": 2, "type": 0, "time_begin": 72141, "time_end": 0, "background": 0}, {"ID": 281, "track": 3, "type": 0, "time_begin": 72329, "time_end": 0, "background": 0}, {"ID": 282, "track": 1, "type": 1, "time_begin": 72516, "time_end": 73079, "background": 0}, {"ID": 283, "track": 3, "type": 0, "time_begin": 73079, "time_end": 0, "background": 0}, {"ID": 284, "track": 4, "type": 0, "time_begin": 73266, "time_end": 0, "background": 0}, {"ID": 285, "track": 2, "type": 0, "time_begin": 73454, "time_end": 0, "background": 0}, {"ID": 286, "track": 4, "type": 0, "time_begin": 73641, "time_end": 0, "background": 0}, {"ID": 287, "track": 2, "type": 0, "time_begin": 73829, "time_end": 0, "background": 0}, {"ID": 288, "track": 1, "type": 1, "time_begin": 74016, "time_end": 74391, "background": 0}, {"ID": 289, "track": 2, "type": 1, "time_begin": 74391, "time_end": 74766, "background": 0}, {"ID": 290, "track": 3, "type": 1, "time_begin": 74766, "time_end": 75516, "background": 0}, {"ID": 291, "track": 4, "type": 1, "time_begin": 75516, "time_end": 76079, "background": 0}, {"ID": 292, "track": 2, "type": 1, "time_begin": 75516, "time_end": 76079, "background": 0}, {"ID": 293, "track": 3, "type": 0, "time_begin": 76079, "time_end": 0, "background": 0}, {"ID": 294, "track": 1, "type": 0, "time_begin": 76266, "time_end": 0, "background": 0}, {"ID": 295, "track": 3, "type": 0, "time_begin": 76454, "time_end": 0, "background": 0}, {"ID": 296, "track": 1, "type": 0, "time_begin": 76641, "time_end": 0, "background": 0}, {"ID": 297, "track": 4, "type": 0, "time_begin": 76829, "time_end": 0, "background": 0}, {"ID": 298, "track": 1, "type": 1, "time_begin": 77016, "time_end": 77391, "background": 0}, {"ID": 299, "track": 2, "type": 1, "time_begin": 77391, "time_end": 77766, "background": 0}, {"ID": 300, "track": 3, "type": 1, "time_begin": 77766, "time_end": 78141, "background": 0}, {"ID": 301, "track": 4, "type": 0, "time_begin": 78141, "time_end": 0, "background": 0}, {"ID": 302, "track": 2, "type": 0, "time_begin": 78329, "time_end": 0, "background": 0}, {"ID": 303, "track": 4, "type": 1, "time_begin": 78516, "time_end": 79079, "background": 0}, {"ID": 304, "track": 2, "type": 0, "time_begin": 79079, "time_end": 0, "background": 0}, {"ID": 305, "track": 3, "type": 0, "time_begin": 79266, "time_end": 0, "background": 0}, {"ID": 306, "track": 1, "type": 0, "time_begin": 79454, "time_end": 0, "background": 0}, {"ID": 307, "track": 3, "type": 0, "time_begin": 79641, "time_end": 0, "background": 0}, {"ID": 308, "track": 2, "type": 0, "time_begin": 79829, "time_end": 0, "background": 0}, {"ID": 309, "track": 1, "type": 0, "time_begin": 80016, "time_end": 0, "background": 0}, {"ID": 310, "track": 3, "type": 0, "time_begin": 80016, "time_end": 0, "background": 0}, {"ID": 311, "track": 2, "type": 0, "time_begin": 80391, "time_end": 0, "background": 0}, {"ID": 312, "track": 4, "type": 0, "time_begin": 80391, "time_end": 0, "background": 0}, {"ID": 313, "track": 3, "type": 0, "time_begin": 80766, "time_end": 0, "background": 0}, {"ID": 314, "track": 1, "type": 0, "time_begin": 80766, "time_end": 0, "background": 0}]
