[
    {
        "ID": 1,
        "track": 2,
        "time_begin": 955,
        "type": 0,
        "time_end": 0
    },
    {
        "ID": 2,
        "track": 2,
        "time_begin": 1687,
        "type": 0,
        "time_end": 0
    },
    {
        "ID": 3,
        "track": 1,
        "time_begin": 2419,
        "type": 0,
        "time_end": 0
    },
    {
        "ID": 4,
        "track": 2,
        "time_begin": 2785,
        "type": 0,
        "time_end": 0
    },
    {
        "ID": 5,
        "track": 2,
        "time_begin": 3151,
        "type": 0,
        "time_end": 0
    },
    {
        "ID": 6,
        "track": 3,
        "time_begin": 3516,
        "type": 0,
        "time_end": 0
    },
    {
        "ID": 7,
        "track": 3,
        "time_begin": 3882,
        "type": 6,
        "time_end": 4614
    },
    {
        "ID": 8,
        "track": 1,
        "time_begin": 3882,
        "type": 2,
        "time_end": 4614
    },
    {
        "ID": 9,
        "track": 2,
        "time_begin": 3882,
        "type": 2,
        "time_end": 4614
    },
    {
        "ID": 10,
        "track": 2,
        "time_begin": 4614,
        "type": 6,
        "time_end": 5346
    },
    {
        "ID": 11,
        "track": 3,
        "time_begin": 4614,
        "type": 2,
        "time_end": 5346
    },
    {
        "ID": 12,
        "track": 2,
        "time_begin": 5346,
        "type": 0,
        "time_end": 0
    },
    {
        "ID": 13,
        "track": 2,
        "time_begin": 5712,
        "type": 0,
        "time_end": 0
    },
    {
        "ID": 14,
        "track": 3,
        "time_begin": 6077,
        "type": 0,
        "time_end": 0
    },
    {
        "ID": 15,
        "track": 2,
        "time_begin": 6443,
        "type": 0,
        "time_end": 0
    },
    {
        "ID": 16,
        "track": 1,
        "time_begin": 6809,
        "type": 0,
        "time_end": 0
    },
    {
        "ID": 17,
        "track": 2,
        "time_begin": 7175,
        "type": 0,
        "time_end": 0
    },
    {
        "ID": 18,
        "track": 2,
        "time_begin": 7358,
        "type": 0,
        "time_end": 0
    },
    {
        "ID": 19,
        "track": 2,
        "time_begin": 7541,
        "type": 0,
        "time_end": 0
    },
    {
        "ID": 20,
        "track": 2,
        "time_begin": 7907,
        "type": 0,
        "time_end": 0
    },
    {
        "ID": 21,
        "track": 3,
        "time_begin": 8273,
        "type": 0,
        "time_end": 0
    },
    {
        "ID": 22,
        "track": 2,
        "time_begin": 8638,
        "type": 0,
        "time_end": 0
    },
    {
        "ID": 23,
        "track": 2,
        "time_begin": 8821,
        "type": 0,
        "time_end": 0
    },
    {
        "ID": 24,
        "track": 2,
        "time_begin": 9004,
        "type": 0,
        "time_end": 0
    },
    {
        "ID": 25,
        "track": 2,
        "time_begin": 9370,
        "type": 0,
        "time_end": 0
    },
    {
        "ID": 26,
        "track": 1,
        "time_begin": 9736,
        "type": 0,
        "time_end": 0
    },
    {
        "ID": 27,
        "track": 2,
        "time_begin": 10102,
        "type": 0,
        "time_end": 0
    },
    {
        "ID": 28,
        "track": 2,
        "time_begin": 10285,
        "type": 0,
        "time_end": 0
    },
    {
        "ID": 29,
        "track": 2,
        "time_begin": 10468,
        "type": 0,
        "time_end": 0
    },
    {
        "ID": 30,
        "track": 2,
        "time_begin": 10833,
        "type": 0,
        "time_end": 0
    },
    {
        "ID": 31,
        "track": 3,
        "time_begin": 11199,
        "type": 2,
        "time_end": 12663
    },
    {
        "ID": 32,
        "track": 2,
        "time_begin": 11199,
        "type": 6,
        "time_end": 12663
    },
    {
        "ID": 33,
        "track": 1,
        "time_begin": 11199,
        "type": 2,
        "time_end": 12663
    },
    {
        "ID": 34,
        "track": 2,
        "time_begin": 11565,
        "type": 3,
        "time_end": 12114
    },
    {
        "ID": 35,
        "track": 2,
        "time_begin": 12663,
        "type": 6,
        "time_end": 13394
    },
    {
        "ID": 36,
        "track": 1,
        "time_begin": 12663,
        "type": 2,
        "time_end": 13394
    },
    {
        "ID": 37,
        "track": 3,
        "time_begin": 12663,
        "type": 2,
        "time_end": 13394
    },
    {
        "ID": 38,
        "track": 2,
        "time_begin": 13394,
        "type": 6,
        "time_end": 14126
    },
    {
        "ID": 39,
        "track": 1,
        "time_begin": 13394,
        "type": 2,
        "time_end": 14126
    },
    {
        "ID": 40,
        "track": 3,
        "time_begin": 13394,
        "type": 2,
        "time_end": 14126
    },
    {
        "ID": 41,
        "track": 1,
        "time_begin": 14126,
        "type": 0,
        "time_end": 0
    },
    {
        "ID": 42,
        "track": 1,
        "time_begin": 14492,
        "type": 0,
        "time_end": 0
    },
    {
        "ID": 43,
        "track": 2,
        "time_begin": 14858,
        "type": 0,
        "time_end": 0
    },
    {
        "ID": 44,
        "track": 2,
        "time_begin": 15224,
        "type": 0,
        "time_end": 0
    },
    {
        "ID": 45,
        "track": 1,
        "time_begin": 15590,
        "type": 2,
        "time_end": 15955
    },
    {
        "ID": 46,
        "track": 3,
        "time_begin": 15590,
        "type": 6,
        "time_end": 15955
    },
    {
        "ID": 47,
        "track": 2,
        "time_begin": 15590,
        "type": 2,
        "time_end": 15955
    },
    {
        "ID": 48,
        "track": 2,
        "time_begin": 15955,
        "type": 6,
        "time_end": 17053
    },
    {
        "ID": 49,
        "track": 3,
        "time_begin": 15955,
        "type": 2,
        "time_end": 17053
    },
    {
        "ID": 50,
        "track": 2,
        "time_begin": 16504,
        "type": 10,
        "time_end": 0
    },
    {
        "ID": 51,
        "track": 2,
        "time_begin": 17053,
        "type": 0,
        "time_end": 0
    },
    {
        "ID": 52,
        "track": 2,
        "time_begin": 17419,
        "type": 0,
        "time_end": 0
    },
    {
        "ID": 53,
        "track": 3,
        "time_begin": 17785,
        "type": 0,
        "time_end": 0
    },
    {
        "ID": 54,
        "track": 2,
        "time_begin": 18151,
        "type": 0,
        "time_end": 0
    },
    {
        "ID": 55,
        "track": 1,
        "time_begin": 18516,
        "type": 0,
        "time_end": 0
    },
    {
        "ID": 56,
        "track": 2,
        "time_begin": 18882,
        "type": 0,
        "time_end": 0
    },
    {
        "ID": 57,
        "track": 2,
        "time_begin": 19065,
        "type": 0,
        "time_end": 0
    },
    {
        "ID": 58,
        "track": 2,
        "time_begin": 19248,
        "type": 0,
        "time_end": 0
    },
    {
        "ID": 59,
        "track": 2,
        "time_begin": 19614,
        "type": 0,
        "time_end": 0
    },
    {
        "ID": 60,
        "track": 1,
        "time_begin": 19980,
        "type": 4,
        "time_end": 0
    },
    {
        "ID": 61,
        "track": 3,
        "time_begin": 19980,
        "type": 0,
        "time_end": 0
    },
    {
        "ID": 62,
        "track": 2,
        "time_begin": 20346,
        "type": 0,
        "time_end": 0
    },
    {
        "ID": 63,
        "track": 2,
        "time_begin": 20529,
        "type": 0,
        "time_end": 0
    },
    {
        "ID": 64,
        "track": 2,
        "time_begin": 20712,
        "type": 0,
        "time_end": 0
    },
    {
        "ID": 65,
        "track": 2,
        "time_begin": 21077,
        "type": 0,
        "time_end": 0
    },
    {
        "ID": 66,
        "track": 1,
        "time_begin": 21443,
        "type": 0,
        "time_end": 0
    },
    {
        "ID": 67,
        "track": 2,
        "time_begin": 21809,
        "type": 0,
        "time_end": 0
    },
    {
        "ID": 68,
        "track": 2,
        "time_begin": 21992,
        "type": 0,
        "time_end": 0
    },
    {
        "ID": 69,
        "track": 2,
        "time_begin": 22175,
        "type": 0,
        "time_end": 0
    },
    {
        "ID": 70,
        "track": 2,
        "time_begin": 22541,
        "type": 0,
        "time_end": 0
    },
    {
        "ID": 71,
        "track": 1,
        "time_begin": 22907,
        "type": 0,
        "time_end": 0
    },
    {
        "ID": 72,
        "track": 3,
        "time_begin": 23272,
        "type": 4,
        "time_end": 0
    },
    {
        "ID": 73,
        "track": 2,
        "time_begin": 23638,
        "type": 0,
        "time_end": 0
    },
    {
        "ID": 74,
        "track": 2,
        "time_begin": 24004,
        "type": 0,
        "time_end": 0
    },
    {
        "ID": 75,
        "track": 2,
        "time_begin": 24370,
        "type": 2,
        "time_end": 25102
    },
    {
        "ID": 76,
        "track": 1,
        "time_begin": 24370,
        "type": 2,
        "time_end": 25102
    },
    {
        "ID": 77,
        "track": 3,
        "time_begin": 24370,
        "type": 6,
        "time_end": 25102
    },
    {
        "ID": 78,
        "track": 3,
        "time_begin": 25102,
        "type": 6,
        "time_end": 25833
    },
    {
        "ID": 79,
        "track": 2,
        "time_begin": 25102,
        "type": 2,
        "time_end": 25833
    },
    {
        "ID": 80,
        "track": 2,
        "time_begin": 25502,
        "type": 14,
        "time_end": 0
    },
    {
        "ID": 81,
        "track": 1,
        "time_begin": 25833,
        "type": 0,
        "time_end": 0
    },
    {
        "ID": 82,
        "track": 1,
        "time_begin": 26199,
        "type": 0,
        "time_end": 0
    },
    {
        "ID": 83,
        "track": 2,
        "time_begin": 26565,
        "type": 0,
        "time_end": 0
    },
    {
        "ID": 84,
        "track": 2,
        "time_begin": 26931,
        "type": 0,
        "time_end": 0
    },
    {
        "ID": 85,
        "track": 3,
        "time_begin": 27297,
        "type": 6,
        "time_end": 28029
    },
    {
        "ID": 86,
        "track": 2,
        "time_begin": 27297,
        "type": 2,
        "time_end": 28029
    },
    {
        "ID": 87,
        "track": 1,
        "time_begin": 27297,
        "type": 2,
        "time_end": 28029
    },
    {
        "ID": 88,
        "track": 2,
        "time_begin": 28029,
        "type": 6,
        "time_end": 28760
    },
    {
        "ID": 89,
        "track": 3,
        "time_begin": 28029,
        "type": 2,
        "time_end": 28760
    },
    {
        "ID": 90,
        "track": 1,
        "time_begin": 28395,
        "type": 10,
        "time_end": 0
    },
    {
        "ID": 91,
        "track": 2,
        "time_begin": 28395,
        "type": 10,
        "time_end": 0
    },
    {
        "ID": 92,
        "track": 3,
        "time_begin": 28395,
        "type": 10,
        "time_end": 0
    },
    {
        "ID": 93,
        "track": 2,
        "time_begin": 28760,
        "type": 0,
        "time_end": 0
    },
    {
        "ID": 94,
        "track": 2,
        "time_begin": 29126,
        "type": 0,
        "time_end": 0
    },
    {
        "ID": 95,
        "track": 3,
        "time_begin": 29492,
        "type": 0,
        "time_end": 0
    },
    {
        "ID": 96,
        "track": 2,
        "time_begin": 29858,
        "type": 0,
        "time_end": 0
    },
    {
        "ID": 97,
        "track": 1,
        "time_begin": 30224,
        "type": 0,
        "time_end": 0
    },
    {
        "ID": 98,
        "track": 2,
        "time_begin": 30590,
        "type": 0,
        "time_end": 0
    },
    {
        "ID": 99,
        "track": 2,
        "time_begin": 30772,
        "type": 0,
        "time_end": 0
    },
    {
        "ID": 100,
        "track": 2,
        "time_begin": 30955,
        "type": 0,
        "time_end": 0
    },
    {
        "ID": 101,
        "track": 2,
        "time_begin": 31321,
        "type": 0,
        "time_end": 0
    },
    {
        "ID": 102,
        "track": 3,
        "time_begin": 31687,
        "type": 0,
        "time_end": 0
    },
    {
        "ID": 103,
        "track": 2,
        "time_begin": 32053,
        "type": 0,
        "time_end": 0
    },
    {
        "ID": 104,
        "track": 2,
        "time_begin": 32236,
        "type": 0,
        "time_end": 0
    },
    {
        "ID": 105,
        "track": 2,
        "time_begin": 32419,
        "type": 0,
        "time_end": 0
    },
    {
        "ID": 106,
        "track": 2,
        "time_begin": 32785,
        "type": 0,
        "time_end": 0
    },
    {
        "ID": 107,
        "track": 1,
        "time_begin": 33151,
        "type": 0,
        "time_end": 0
    },
    {
        "ID": 108,
        "track": 2,
        "time_begin": 33516,
        "type": 0,
        "time_end": 0
    },
    {
        "ID": 109,
        "track": 2,
        "time_begin": 33699,
        "type": 0,
        "time_end": 0
    },
    {
        "ID": 110,
        "track": 2,
        "time_begin": 33882,
        "type": 0,
        "time_end": 0
    },
    {
        "ID": 111,
        "track": 2,
        "time_begin": 34248,
        "type": 0,
        "time_end": 0
    },
    {
        "ID": 112,
        "track": 3,
        "time_begin": 34614,
        "type": 0,
        "time_end": 0
    },
    {
        "ID": 113,
        "track": 3,
        "time_begin": 34980,
        "type": 0,
        "time_end": 0
    },
    {
        "ID": 114,
        "track": 1,
        "time_begin": 36077,
        "type": 0,
        "time_end": 0
    },
    {
        "ID": 115,
        "track": 1,
        "time_begin": 36260,
        "type": 0,
        "time_end": 0
    },
    {
        "ID": 116,
        "track": 1,
        "time_begin": 36443,
        "type": 0,
        "time_end": 0
    },
    {
        "ID": 117,
        "track": 1,
        "time_begin": 36626,
        "type": 0,
        "time_end": 0
    },
    {
        "ID": 118,
        "track": 1,
        "time_begin": 36992,
        "type": 0,
        "time_end": 0
    },
    {
        "ID": 119,
        "track": 1,
        "time_begin": 37175,
        "type": 0,
        "time_end": 0
    }
]
